ceilfeat/__init__.py
ceilfeat/clouds.py
ceilfeat/denoise.py
ceilfeat/flags.py
ceilfeat/io.py
ceilfeat/layers.py
ceilfeat/pipeline.py
ceilfeat/precip.py
ceilfeat/thresholds.py
ceilfeat/wavelet.py
ceilfeat-0.1.2.dist-info/METADATA
ceilfeat-0.1.2.dist-info/WHEEL
ceilfeat-0.1.2.dist-info/entry_points.txt
ceilfeat-0.1.2.dist-info/licenses/LICENSE
ceilfeat-0.1.2.dist-info/RECORD
