Metadata-Version: 2.4
Name: ceilfeat
Version: 0.1.2
Summary: Ceilometer feature detection (clouds, precip, fog, layers) from NetCDF.
Project-URL: Homepage, https://github.com/DanielWefer/ceil-feature-detection
Project-URL: Issues, https://github.com/DanielWefer/ceil-feature-detection/issues
Author-email: Daniel Wefer <dweef1@gmail.com>
License:                   GNU LESSER GENERAL PUBLIC LICENSE
License-File: LICENSE
Classifier: Intended Audience :: Science/Research
Classifier: License :: OSI Approved :: GNU Lesser General Public License v2 or later (LGPLv2+)
Classifier: Programming Language :: Python :: 3
Classifier: Programming Language :: Python :: 3 :: Only
Classifier: Topic :: Scientific/Engineering :: Atmospheric Science
Requires-Python: >=3.9
Requires-Dist: act-atmos
Requires-Dist: numpy
Requires-Dist: opencv-python
Requires-Dist: pandas
Requires-Dist: scikit-image
Requires-Dist: xarray
Provides-Extra: dev
Requires-Dist: build; extra == 'dev'
Requires-Dist: mypy; extra == 'dev'
Requires-Dist: pytest; extra == 'dev'
Requires-Dist: ruff; extra == 'dev'
Requires-Dist: twine; extra == 'dev'
